ai_cosmos_toolkit/__init__.py
ai_cosmos_toolkit/cosmos_client.py
ai_cosmos_toolkit/openai_client.py
ai_cosmos_toolkit/orchestrator.py
ai_cosmos_toolkit-0.1.1.dist-info/METADATA
ai_cosmos_toolkit-0.1.1.dist-info/WHEEL
ai_cosmos_toolkit-0.1.1.dist-info/top_level.txt
ai_cosmos_toolkit-0.1.1.dist-info/RECORD
