Metadata-Version: 2.4
Name: ai-cosmos-toolkit
Version: 0.1.1
Summary: Reusable toolkit integrating Azure OpenAI and Cosmos DB for semantic search
Home-page: https://github.com/vamsichowdaryg/AI_Cosmos_Toolkit
Author: Vamsi Gudapati
Author-email: vamsi7673916775@gmail.com
License: MIT
Classifier: Programming Language :: Python :: 3
Classifier: License :: OSI Approved :: MIT License
Classifier: Operating System :: OS Independent
Classifier: Topic :: Software Development :: Libraries :: Python Modules
Classifier: Intended Audience :: Developers
Requires-Python: >=3.8
Requires-Dist: openai>=1.3.0
Requires-Dist: azure-cosmos>=4.5.0
Dynamic: author
Dynamic: author-email
Dynamic: classifier
Dynamic: description-content-type
Dynamic: home-page
Dynamic: license
Dynamic: requires-dist
Dynamic: requires-python
Dynamic: summary
